abstractsemantics/__init__.py
abstractsemantics/registry.py
abstractsemantics/schema.py
abstractsemantics/semantics.yaml
abstractsemantics-0.0.1.dist-info/METADATA
abstractsemantics-0.0.1.dist-info/WHEEL
abstractsemantics-0.0.1.dist-info/top_level.txt
abstractsemantics-0.0.1.dist-info/RECORD
