Metadata-Version: 2.4
Name: abstractsemantics
Version: 0.0.1
Summary: Semantics registry (predicates/types) for AbstractFramework.
Author: Laurent-Philippe Albou
License: MIT
Requires-Python: >=3.10
Requires-Dist: PyYAML>=6.0
Provides-Extra: dev
Requires-Dist: pytest>=7.0.0; extra == "dev"
